pgcrypto/__init__.py
pgcrypto/base.py
pgcrypto/fields.py
pgcrypto/functions.py
django_pgcrypto-3.1.0.dist-info/WHEEL
django_pgcrypto-3.1.0.dist-info/METADATA
django_pgcrypto-3.1.0.dist-info/RECORD
