Metadata-Version: 2.3
Name: django-pgcrypto
Version: 3.1.0
Summary: Python and Django utilities for encrypted fields using pgcrypto.
Author: Dan Watson
Author-email: Dan Watson <dcwatson@gmail.com>
License: BSD-2-Clause
Classifier: Development Status :: 5 - Production/Stable
Classifier: Framework :: Django
Classifier: Programming Language :: Python :: 3
Classifier: Topic :: Database
Requires-Dist: cryptography
Requires-Python: >=3.8
Project-URL: Repository, https://github.com/dcwatson/django-pgcrypto
